together_forever/__init__.py
together_forever/together_forever.py
together_forever/version.py
together_forever-1.0.6.dist-info/LICENSE.txt
together_forever-1.0.6.dist-info/METADATA
together_forever-1.0.6.dist-info/WHEEL
together_forever-1.0.6.dist-info/top_level.txt
together_forever-1.0.6.dist-info/RECORD
