Metadata-Version: 2.1
Name: together_forever
Version: 1.0.6
Summary: A Python package capable of crawling Facebook page information.
Home-page: https://github.com/wael-sudo2/together-forever
Download-URL: https://github.com//wael-sudo2/together-forever/archive/refs/tags/v1.0.3.tar.gz
Author: Wael Hkiri
Author-email: wael.hkiri.dev@gmail.com
License: MIT
Keywords: facebook scraping,scraping,facebook crawler,facebook page,selenium,crawler,scraper,facebook
Classifier: Development Status :: 5 - Production/Stable
Classifier: Intended Audience :: Developers
Classifier: Topic :: Software Development :: Build Tools
Classifier: License :: OSI Approved :: MIT License
Classifier: Programming Language :: Python
Classifier: Programming Language :: Python :: 3.10
Requires-Python: >=3.10
License-File: LICENSE.txt
Requires-Dist: geopy==2.2.0
Requires-Dist: retry~=0.9.2
Requires-Dist: selenium~=4.8.2
Requires-Dist: googletrans~=4.0.0rc1
